COPYING
MANIFEST.in
Makefile
NEWS
README.txt
__pkginfo__.py
make-check-filter.py
setup.cfg
setup.py
pydbgr/VERSION.py
pydbgr/__init__.py
pydbgr/api.py
pydbgr/bwcli.py
pydbgr/cli.py
pydbgr/client.py
pydbgr/clifns.py
pydbgr/debugger.py
pydbgr/exception.py
pydbgr/interface.py
pydbgr/misc.py
pydbgr/post_mortem.py
pydbgr/vprocessor.py
pydbgr.egg-info/PKG-INFO
pydbgr.egg-info/SOURCES.txt
pydbgr.egg-info/dependency_links.txt
pydbgr.egg-info/entry_points.txt
pydbgr.egg-info/namespace_packages.txt
pydbgr.egg-info/not-zip-safe
pydbgr.egg-info/requires.txt
pydbgr.egg-info/top_level.txt
pydbgr/bwprocessor/__init__.py
pydbgr/bwprocessor/location.py
pydbgr/bwprocessor/main.py
pydbgr/bwprocessor/msg.py
pydbgr/interfaces/__init__.py
pydbgr/interfaces/bullwinkle.py
pydbgr/interfaces/client.py
pydbgr/interfaces/comcodes.py
pydbgr/interfaces/script.py
pydbgr/interfaces/server.py
pydbgr/interfaces/user.py
pydbgr/io/__init__.py
pydbgr/io/base_io.py
pydbgr/io/fifoclient.py
pydbgr/io/fifoserver.py
pydbgr/io/input.py
pydbgr/io/output.py
pydbgr/io/scriptin.py
pydbgr/io/stringarray.py
pydbgr/io/tcpclient.py
pydbgr/io/tcpfns.py
pydbgr/io/tcpserver.py
pydbgr/lib/__init__.py
pydbgr/lib/breakpoint.py
pydbgr/lib/bytecode.py
pydbgr/lib/core.py
pydbgr/lib/default.py
pydbgr/lib/disassemble.py
pydbgr/lib/display.py
pydbgr/lib/eval.py
pydbgr/lib/file.py
pydbgr/lib/format-new.py
pydbgr/lib/format.py
pydbgr/lib/pp.py
pydbgr/lib/print.py
pydbgr/lib/sighandler.py
pydbgr/lib/stack.py
pydbgr/lib/thread.py
pydbgr/processor/__init__.py
pydbgr/processor/cmdbreak.py
pydbgr/processor/cmdfns.py
pydbgr/processor/cmdproc.py
pydbgr/processor/subcmd.py
pydbgr/processor/trace.py
pydbgr/processor/command/__init__.py
pydbgr/processor/command/alias.py
pydbgr/processor/command/backtrace.py
pydbgr/processor/command/base_cmd.py
pydbgr/processor/command/base_subcmd.py
pydbgr/processor/command/base_submgr.py
pydbgr/processor/command/break.py
pydbgr/processor/command/cd.py
pydbgr/processor/command/condition.py
pydbgr/processor/command/continue.py
pydbgr/processor/command/debug.py
pydbgr/processor/command/delete.py
pydbgr/processor/command/disable.py
pydbgr/processor/command/disassemble.py
pydbgr/processor/command/display.py
pydbgr/processor/command/down.py
