Metadata-Version: 1.0
Name: pydbgr
Version: 0.2.6
Summary: Modular Python Debugger
Home-page: http://code.google.com/p/pydbgr/
Author: Rocky Bernstein
Author-email: rocky@gnu.org
License: GPL
Platform: UNKNOWN
Classifier: Development Status :: 4 - Beta
Classifier: Environment :: Console
Classifier: Intended Audience :: Developers
Classifier: License :: OSI Approved :: GNU General Public License (GPL)
Classifier: Operating System :: OS Independent
Classifier: Programming Language :: Python
Classifier: Topic :: Software Development :: Debuggers
Classifier: Topic :: Software Development :: Libraries :: Python Modules
